{
  "schemas": [
    {
      "id": 1,
      "descricao": "arquivo iSIMP",
      "ativo": true,
      "publico": true,
      "tipo": "posicao",
      "createdAt": "2023-01-19T22:56:37.989Z"
    },
    {
      "id": 2,
      "descricao": "etiqueta maquina 1",
      "ativo": true,
      "publico": true,
      "tipo": "caractere",
      "createdAt": "2023-01-19T22:55:37.989Z"
    },
    {
      "descricao": "mais um teste",
      "ativo": false,
      "publico": true,
      "tipo": "caractere",
      "createdAt": "2023-01-24T01:06:27.488Z",
      "id": 3
    },
    {
      "descricao": "mais um outro teste",
      "ativo": false,
      "publico": true,
      "tipo": "caractere",
      "createdAt": "2023-01-24T01:16:07.065Z",
      "id": 5
    },
    {
      "descricao": "arquivo Prati",
      "ativo": true,
      "publico": true,
      "createdAt": "2023-02-04T19:02:53.156Z",
      "id": 6
    }
  ],
  "regras": [
    {
      "esquemaID": 1,
      "id": 1,
      "sequencia": "3",
      "inicial": 1,
      "final": 10,
      "tamanho": 3,
      "tipo": "caractere",
      "descricao": "codigo do usuario"
    },
    {
      "esquemaID": 1,
      "id": 2,
      "sequencia": "1",
      "inicial": 11,
      "final": 14,
      "tamanho": 20,
      "tipo": "caractere",
      "descricao": "nome do usuario"
    },
    {
      "esquemaID": 1,
      "id": 3,
      "sequencia": "2",
      "inicial": 15,
      "final": 20,
      "tamanho": 14,
      "tipo": "caractere",
      "descricao": "CPF/CNPJ"
    },
    {
      "esquemaID": 1,
      "id": 4,
      "sequencia": "8",
      "inicial": 15,
      "final": 20,
      "tamanho": 6,
      "tipo": "caractere",
      "descricao": "quarto campo"
    },
    {
      "esquemaID": 1,
      "id": 5,
      "sequencia": "6",
      "inicial": 15,
      "final": 20,
      "tamanho": 3,
      "tipo": "caractere",
      "descricao": "Lorem ipsum dolor sit amet, consectetur adipiscing elit. Sed vulputate luctus feugiat. "
    },
    {
      "esquemaID": 1,
      "id": 6,
      "sequencia": "4",
      "inicial": 15,
      "final": 20,
      "tamanho": 3,
      "tipo": "caractere",
      "descricao": "SEXTO campo"
    },
    {
      "esquemaID": 1,
      "id": 7,
      "sequencia": "7",
      "inicial": 15,
      "final": 20,
      "tamanho": 3,
      "tipo": "caractere",
      "descricao": "setimo campo"
    },
    {
      "sequencia": "5",
      "tamanho": "30",
      "descricao": "teste",
      "id": 8
    }
  ]
}